CleverFetch/CleverFetch.py
CleverFetch/__init__.py
cleverfetch_pkg_dmarienburg-1.0.dist-info/LICENSE
cleverfetch_pkg_dmarienburg-1.0.dist-info/METADATA
cleverfetch_pkg_dmarienburg-1.0.dist-info/WHEEL
cleverfetch_pkg_dmarienburg-1.0.dist-info/top_level.txt
cleverfetch_pkg_dmarienburg-1.0.dist-info/RECORD
