Metadata-Version: 2.1
Name: cleverfetch-pkg-dmarienburg
Version: 1.0
Summary: A simple script for automating your downloads of data from the Clever sftp site
Home-page: https://github.com/dmarienburg/CleverFetch
Author: David Marienburg
Author-email: david.marienburg@gmail.com
License: UNKNOWN
Platform: UNKNOWN
Classifier: Programming Language :: Python :: 3
Classifier: License :: OSI Approved :: MIT License
Classifier: Operating System :: OS Independent
Requires-Python: >=3.0
